LICENSE.txt
MANIFEST.in
setup.py
r2c1/__init__.py
r2c1/r2_tokenize.py
r2c1/r2c1_const.py
r2c1/r2c1_main.py
r2c1.egg-info/PKG-INFO
r2c1.egg-info/SOURCES.txt
r2c1.egg-info/dependency_links.txt
r2c1.egg-info/requires.txt
r2c1.egg-info/top_level.txt
r2c1/test/r2c1.conf
r2c1/test/test_r2_main.py