Metadata-Version: 1.1
Name: r2c1
Version: 1.0.2
Summary: Convert string like command with args and options to json
Home-page: https://github.com/chinapnr/r2c1
Author: david.yi
Author-email: wingfish@gmail.com
License: MIT
Platform: UNKNOWN
Classifier: Development Status :: 3 - Alpha
Classifier: Intended Audience :: Developers
Classifier: Topic :: Software Development :: Build Tools
Classifier: License :: OSI Approved :: MIT License
Classifier: Programming Language :: Python :: 3.4
Classifier: Programming Language :: Python :: 3.5
